gqlbridge/__init__.py
gqlbridge/core.py
gqlbridge-1.0.5.dist-info/licenses/LICENSE
gqlbridge-1.0.5.dist-info/METADATA
gqlbridge-1.0.5.dist-info/WHEEL
gqlbridge-1.0.5.dist-info/top_level.txt
gqlbridge-1.0.5.dist-info/RECORD
