Metadata-Version: 2.4
Name: gqlbridge
Version: 1.0.5
Summary: Execute GraphQL-style queries on PostgreSQL and return nested JSON results.
Author-email: Harshavardhan Chitakana <chharshavardhan2001@gmail.com>
License: MIT
Project-URL: Homepage, https://github.com/HarshaChitakana/GQLBridge
Project-URL: Documentation, https://github.com/HarshaChitakana/GQLBridge#readme
Project-URL: Repository, https://github.com/HarshaChitakana/GQLBridge
Keywords: GraphQL,SQL,PostgreSQL,JSON,ETL,Data Engineering
Classifier: Programming Language :: Python :: 3
Classifier: License :: OSI Approved :: MIT License
Classifier: Operating System :: OS Independent
Classifier: Intended Audience :: Developers
Classifier: Topic :: Database
Classifier: Topic :: Software Development :: Libraries :: Python Modules
Requires-Python: >=3.9
License-File: LICENSE
Requires-Dist: graphql-core>=3.2.3
Requires-Dist: sqlalchemy>=2.0.0
Requires-Dist: pandas>=1.5.0
Requires-Dist: PyYAML>=6.0
Requires-Dist: psycopg2-binary>=2.9.0
Dynamic: license-file
